omforme/__init__.py
omforme/__main__.py
omforme/cli.py
omforme/omforme.py
omforme-2023.6.18.dist-info/LICENSE
omforme-2023.6.18.dist-info/METADATA
omforme-2023.6.18.dist-info/WHEEL
omforme-2023.6.18.dist-info/entry_points.txt
omforme-2023.6.18.dist-info/top_level.txt
omforme-2023.6.18.dist-info/RECORD
